{
  "Настройки шкафа": {
    "skinID выдаваемоего шкафа": 2679214470,
    "Радиус в котором выдаются налоги (в метрах)": 1000,
    "Сколько нужно секунд для захвата": 12,
    "Откат между захватами в секундах": 100,
    "Процент налога": 10
  },
  "Настройки маркера": {
    "Радиус маркера": 0.9,
    "Прозрачность маркера": 0.4,
    "Цвет маркера когда можно захватить": "#10c916",
    "Цвет маркера когда идет захват": "#ed0707",
    "Цвет маркера когда нельзя захватить": "#ffb700"
  },
  "Config version": {
    "Major": 1,
    "Minor": 0,
    "Patch": 6
  }
}