{
  "Визуализация запросов к серверу": false,
  "Настройки префиксов": {
    "Доступные для выбора префикмсы": [
      {
        "Название в интерфейсе": "ИГРОК",
        "Значение в чате (может быть пустым)": "ИГРОК",
        "Привилегия (wchat.<name> или пусто)": ""
      },
      {
        "Название в интерфейсе": "SHOOTER",
        "Значение в чате (может быть пустым)": "SHOOTER",
        "Привилегия (wchat.<name> или пусто)": "wchat.shooter"
      },
      {
        "Название в интерфейсе": "KNIGHT",
        "Значение в чате (может быть пустым)": "KNIGHT",
        "Привилегия (wchat.<name> или пусто)": "wchat.knight"
      },
      {
        "Название в интерфейсе": "MONARCH",
        "Значение в чате (может быть пустым)": "MONARCH",
        "Привилегия (wchat.<name> или пусто)": "wchat.monarch"
      },
      {
        "Название в интерфейсе": "PRINCE",
        "Значение в чате (может быть пустым)": "PRINCE",
        "Привилегия (wchat.<name> или пусто)": "wchat.prince"
      },
      {
        "Название в интерфейсе": "МОДЕРАТОР",
        "Значение в чате (может быть пустым)": "МОДЕРАТОР",
        "Привилегия (wchat.<name> или пусто)": "wchat.moderator"
      },
      {
        "Название в интерфейсе": "АДМИН",
        "Значение в чате (может быть пустым)": "АДМИНИСТРАТОР",
        "Привилегия (wchat.<name> или пусто)": "wchat.admin"
      },
      {
        "Название в интерфейсе": "ГЛ.АДМИН",
        "Значение в чате (может быть пустым)": "ГЛ.АДМИНИСТРАТОР",
        "Привилегия (wchat.<name> или пусто)": "wchat.gladmin"
      },
      {
        "Название в интерфейсе": "戦闘コミュニティ",
        "Значение в чате (может быть пустым)": "戦闘コミュニティ",
        "Привилегия (wchat.<name> или пусто)": "wchat.custom1"
      }
    ],
    "Доступные для выбора цвета": [
      {
        "Название в интерфейсе": "СТАНДАРТНЫЙ",
        "Значение в чате (может быть пустым)": "#FFFFFF",
        "Привилегия (wchat.<name> или пусто)": ""
      },
      {
        "Название в интерфейсе": "SHOOTER",
        "Значение в чате (может быть пустым)": "#7CFC00",
        "Привилегия (wchat.<name> или пусто)": "wchat.prefixColorShooter"
      },
      {
        "Название в интерфейсе": "KNIGHT",
        "Значение в чате (может быть пустым)": "#B22222",
        "Привилегия (wchat.<name> или пусто)": "wchat.prefixColorKnight"
      },
      {
        "Название в интерфейсе": "MONARCH",
        "Значение в чате (может быть пустым)": "#A9A9A9",
        "Привилегия (wchat.<name> или пусто)": "wchat.prefixColorMonarch"
      },
      {
        "Название в интерфейсе": "PRINCE",
        "Значение в чате (может быть пустым)": "#B8860B",
        "Привилегия (wchat.<name> или пусто)": "wchat.prefixColorPrince"
      },
      {
        "Название в интерфейсе": "GL.ADMIN",
        "Значение в чате (может быть пустым)": "#FF4500",
        "Привилегия (wchat.<name> или пусто)": "wchat.prefixColorgladmin"
      },
      {
        "Название в интерфейсе": "戦闘コミュニティ",
        "Значение в чате (может быть пустым)": "#000000",
        "Привилегия (wchat.<name> или пусто)": "wchat.prefixColorCustom"
      }
    ],
    "Доступные для выбора скобки": [
      {
        "Название в интерфейсе": "СТАНДАРТНЫЙ",
        "Значение в чате (может быть пустым)": "%PREFFIX% | ",
        "Привилегия (wchat.<name> или пусто)": ""
      },
      {
        "Название в интерфейсе": "СКОБКИ",
        "Значение в чате (может быть пустым)": "[%PREFFIX%]",
        "Привилегия (wchat.<name> или пусто)": "wchat.hooks"
      },
      {
        "Название в интерфейсе": "ОБЫЧНЫЙ",
        "Значение в чате (может быть пустым)": "%PREFFIX%",
        "Привилегия (wchat.<name> или пусто)": "wchat.hooks"
      },
      {
        "Название в интерфейсе": "ОБЫЧНЫЙ",
        "Значение в чате (может быть пустым)": "%PREFFIX%",
        "Привилегия (wchat.<name> или пусто)": "wchat.hooks"
      }
    ]
  },
  "Настройки имён": {
    "Доступные для выбора цвета": [
      {
        "Название в интерфейсе": "СТАНДАРТНЫЙ",
        "Значение в чате (может быть пустым)": "#FFFFFF",
        "Привилегия (wchat.<name> или пусто)": ""
      },
      {
        "Название в интерфейсе": "SHOOTER",
        "Значение в чате (может быть пустым)": "#7CFC00",
        "Привилегия (wchat.<name> или пусто)": "wchat.prefixCShooter"
      },
      {
        "Название в интерфейсе": "KNIGHT",
        "Значение в чате (может быть пустым)": "#B22222",
        "Привилегия (wchat.<name> или пусто)": "wchat.prefixCKnight"
      },
      {
        "Название в интерфейсе": "MONARCH",
        "Значение в чате (может быть пустым)": "#A9A9A9",
        "Привилегия (wchat.<name> или пусто)": "wchat.prefixCMonarch"
      },
      {
        "Название в интерфейсе": "PRINCE",
        "Значение в чате (может быть пустым)": "#B8860B",
        "Привилегия (wchat.<name> или пусто)": "wchat.prefixCPrince"
      },
      {
        "Название в интерфейсе": "GL.ADMIN",
        "Значение в чате (может быть пустым)": "#FF4500",
        "Привилегия (wchat.<name> или пусто)": "wchat.prefixgladmin"
      },
      {
        "Название в интерфейсе": "戦闘コミュニティ",
        "Значение в чате (может быть пустым)": "#000000",
        "Привилегия (wchat.<name> или пусто)": "wchat.prefixgCustom"
      }
    ]
  },
  "Настройки сообщений": {
    "Доступные для выбора цвета": [
      {
        "Название в интерфейсе": "СТАНДАРТНЫЙ",
        "Значение в чате (может быть пустым)": "#FFFFFF",
        "Привилегия (wchat.<name> или пусто)": ""
      },
      {
        "Название в интерфейсе": "SHOOTER",
        "Значение в чате (может быть пустым)": "#7CFC00",
        "Привилегия (wchat.<name> или пусто)": "wchat.pShooter"
      },
      {
        "Название в интерфейсе": "KNIGHT",
        "Значение в чате (может быть пустым)": "#B22222",
        "Привилегия (wchat.<name> или пусто)": "wchat.pKnight"
      },
      {
        "Название в интерфейсе": "MONARCH",
        "Значение в чате (может быть пустым)": "#A9A9A9",
        "Привилегия (wchat.<name> или пусто)": "wchat.pMonarch"
      },
      {
        "Название в интерфейсе": "PRINCE",
        "Значение в чате (может быть пустым)": "#B8860B",
        "Привилегия (wchat.<name> или пусто)": "wchat.pPrince"
      },
      {
        "Название в интерфейсе": "Gl.ADMIN",
        "Значение в чате (может быть пустым)": "#FF4500",
        "Привилегия (wchat.<name> или пусто)": "wchat.Gladmin"
      },
      {
        "Название в интерфейсе": "Gl.ADMIN",
        "Значение в чате (может быть пустым)": "#FF4500",
        "Привилегия (wchat.<name> или пусто)": "wchat.Gladmin"
      }
    ]
  },
  "Настройки мутов": {
    "Стандартное количество часов": 0,
    "Стандартное количество минут": 30,
    "Стандартное количество секунд": 0,
    "Возможные причины для репортов": [
      "Общие нарушения чата",
      "Оскорбление",
      "Клевета"
    ]
  },
  "Настройки авто-сообщений": [],
  "Интервал авто-сообщений": 300,
  "Интервал между сообщения (в сек., анти-флуд)": 3,
  "Ссылка на профиль стима (аватар будет использоваться в глоб. сообщениях)": 0,
  "Настройки цензуры (и их исключений, принимает формат MoscowOVH)": {}
}