{
  "WipeNumber": 227,
  "Items": [
    {
      "ID": -194953424,
      "Position": 0,
      "Amount": 1,
      "Skin": 2289476947,
      "Condition": 271.9145,
      "MaxCondition": 320.0
    },
    {
      "ID": 1545779598,
      "Position": 1,
      "Amount": 1,
      "Skin": 2849939632,
      "Condition": 123.5,
      "MaxCondition": 150.0,
      "Ammo": 29,
      "AmmoType": 605467368,
      "Contents": [
        {
          "ID": 2005491391,
          "Position": 0,
          "Amount": 1,
          "Condition": 100.0,
          "MaxCondition": 100.0
        },
        {
          "ID": 442289265,
          "Position": 1,
          "Amount": 1,
          "Condition": 300.0,
          "MaxCondition": 300.0
        },
        {
          "ID": -132516482,
          "Position": 2,
          "Amount": 1,
          "Condition": 300.0,
          "MaxCondition": 300.0
        }
      ]
    },
    {
      "ID": 254522515,
      "Position": 2,
      "Amount": 23
    },
    {
      "ID": 1850456855,
      "Position": 3,
      "Amount": 1,
      "Skin": 2730616924,
      "Condition": 131.2505,
      "MaxCondition": 150.0
    },
    {
      "ID": 1545779598,
      "Position": 4,
      "Amount": 1,
      "Skin": 2849939632,
      "Condition": 143.25,
      "MaxCondition": 150.0,
      "Ammo": 11,
      "AmmoType": -1211166256,
      "Contents": [
        {
          "ID": 442289265,
          "Position": 0,
          "Amount": 1,
          "Condition": 300.0,
          "MaxCondition": 300.0
        },
        {
          "ID": -132516482,
          "Position": 1,
          "Amount": 1,
          "Condition": 300.0,
          "MaxCondition": 300.0
        },
        {
          "ID": 2005491391,
          "Position": 2,
          "Amount": 1,
          "Condition": 100.0,
          "MaxCondition": 100.0
        }
      ]
    },
    {
      "ID": 1545779598,
      "Position": 5,
      "Amount": 1,
      "Skin": 2849939632,
      "Condition": 111.0,
      "MaxCondition": 150.0,
      "Ammo": 11,
      "AmmoType": 605467368,
      "Contents": [
        {
          "ID": -132516482,
          "Position": 0,
          "Amount": 1
        },
        {
          "ID": 2005491391,
          "Position": 1,
          "Amount": 1
        },
        {
          "ID": 442289265,
          "Position": 2,
          "Amount": 1
        }
      ]
    },
    {
      "ID": 1545779598,
      "Position": 6,
      "Amount": 1,
      "Skin": 2849939632,
      "Condition": 147.0,
      "MaxCondition": 150.0,
      "Ammo": 29,
      "AmmoType": 605467368,
      "Contents": []
    },
    {
      "ID": 1110385766,
      "Position": 7,
      "Amount": 1,
      "Skin": 2365727275,
      "Condition": 184.9174,
      "MaxCondition": 360.0
    },
    {
      "ID": 1545779598,
      "Position": 8,
      "Amount": 1,
      "Skin": 2849939632,
      "Condition": 87.5,
      "MaxCondition": 150.0,
      "Ammo": 38,
      "AmmoType": 605467368,
      "Contents": [
        {
          "ID": -132516482,
          "Position": 0,
          "Amount": 1
        },
        {
          "ID": 442289265,
          "Position": 1,
          "Amount": 1
        },
        {
          "ID": 2005491391,
          "Position": 2,
          "Amount": 1
        }
      ]
    },
    {
      "ID": -194953424,
      "Position": 9,
      "Amount": 1,
      "Skin": 853848770,
      "Condition": 286.621735,
      "MaxCondition": 320.0
    },
    {
      "ID": -194953424,
      "Position": 10,
      "Amount": 1,
      "Skin": 900645045,
      "Condition": 195.0,
      "MaxCondition": 320.0
    },
    {
      "ID": 1850456855,
      "Position": 11,
      "Amount": 1,
      "Skin": 801837047,
      "Condition": 100.130051,
      "MaxCondition": 150.0
    },
    {
      "ID": 1931713481,
      "Position": 12,
      "Amount": 19
    },
    {
      "ID": -1211166256,
      "Position": 13,
      "Amount": 871
    },
    {
      "ID": 1545779598,
      "Position": 14,
      "Amount": 1,
      "Skin": 2849939632,
      "Condition": 114.75,
      "MaxCondition": 150.0,
      "Ammo": 30,
      "AmmoType": 605467368,
      "Contents": [
        {
          "ID": 442289265,
          "Position": 0,
          "Amount": 1
        },
        {
          "ID": -132516482,
          "Position": 1,
          "Amount": 1
        }
      ]
    },
    {
      "ID": -194953424,
      "Position": 15,
      "Amount": 1,
      "Skin": 853848770,
      "Condition": 128.03743,
      "MaxCondition": 320.0
    },
    {
      "ID": 1545779598,
      "Position": 16,
      "Amount": 1,
      "Skin": 2849939632,
      "Condition": 126.5,
      "MaxCondition": 150.0,
      "Ammo": 32,
      "AmmoType": 605467368,
      "Contents": [
        {
          "ID": 442289265,
          "Position": 0,
          "Amount": 1
        },
        {
          "ID": -132516482,
          "Position": 1,
          "Amount": 1
        },
        {
          "ID": 2005491391,
          "Position": 2,
          "Amount": 1
        }
      ]
    },
    {
      "ID": 1110385766,
      "Position": 17,
      "Amount": 1,
      "Skin": 2365727275,
      "Condition": 191.8527,
      "MaxCondition": 360.0
    },
    {
      "ID": 1850456855,
      "Position": 18,
      "Amount": 1,
      "Skin": 2730616924,
      "Condition": 83.5493546,
      "MaxCondition": 150.0
    },
    {
      "ID": 1110385766,
      "Position": 19,
      "Amount": 1,
      "Skin": 2365727275,
      "Condition": 336.2556,
      "MaxCondition": 360.0
    },
    {
      "ID": -194953424,
      "Position": 20,
      "Amount": 2,
      "Skin": 853848770,
      "Condition": 320.0,
      "MaxCondition": 320.0
    },
    {
      "ID": 1850456855,
      "Position": 21,
      "Amount": 1,
      "Skin": 2730616924,
      "Condition": 98.57053,
      "MaxCondition": 150.0
    },
    {
      "ID": 1545779598,
      "Position": 22,
      "Amount": 1,
      "Skin": 2849939632,
      "Condition": 127.0,
      "MaxCondition": 150.0,
      "Ammo": 11,
      "AmmoType": 605467368,
      "Contents": [
        {
          "ID": 2005491391,
          "Position": 0,
          "Amount": 1,
          "Condition": 100.0,
          "MaxCondition": 100.0
        },
        {
          "ID": 442289265,
          "Position": 1,
          "Amount": 1,
          "Condition": 300.0,
          "MaxCondition": 300.0
        },
        {
          "ID": -132516482,
          "Position": 2,
          "Amount": 1,
          "Condition": 300.0,
          "MaxCondition": 300.0
        }
      ]
    },
    {
      "ID": 605467368,
      "Position": 23,
      "Amount": 405
    },
    {
      "ID": -2099697608,
      "Position": 24,
      "Amount": 100000
    },
    {
      "ID": -2099697608,
      "Position": 25,
      "Amount": 100000
    },
    {
      "ID": -1157596551,
      "Position": 26,
      "Amount": 54404
    },
    {
      "ID": -2099697608,
      "Position": 27,
      "Amount": 100000
    },
    {
      "ID": 1545779598,
      "Position": 28,
      "Amount": 1,
      "Skin": 2849939632,
      "Condition": 70.5,
      "MaxCondition": 150.0,
      "Ammo": 33,
      "AmmoType": 605467368,
      "Contents": [
        {
          "ID": -132516482,
          "Position": 1,
          "Amount": 1,
          "MaxCondition": 300.0
        },
        {
          "ID": 2005491391,
          "Position": 2,
          "Amount": 1,
          "MaxCondition": 100.0
        },
        {
          "ID": 442289265,
          "Position": 0,
          "Amount": 1
        }
      ]
    },
    {
      "ID": -4031221,
      "Position": 29,
      "Amount": 123858
    }
  ],
  "OwnerID": 76561199117057202
}